{
    "board": [
        {
            "no": "1",
            "title": "나를 소개합니다.",
            "content": "저는 동양미래대학교에 재학중인 컴퓨터소프트웨어공학과 2-YA 20202296 전채린입니다. 열심히 일하고, 함께 일하고, 즐겁게 일하면 모두가 만족할 수 있는 결과를 낼 수 있다고 믿습니다. 제 이력서를 보시고 제게 관심이 있으시다면 언제든지 연락주세요.",
            "view": "1"
        },
        {
            "no": "2",
            "title": "나의 프로필",
            "content": "다양한 합동작업에서 창의적이고 뛰어난 사람과 함께 일하며 영향을 받을 수 있었다는 건 제 경력을 통틀어 가장 중요한 경험이자 행운입니다. 그를 통해 혼자 일하는 것보다 모두가 함께할 때 더 큰 시너지효과를 볼 수 있단 걸 알게 되었습니다. 이와 관련하여 제 과거 프로젝트, 그리고 최근 프로젝트에 대해 궁금하신 점이 있다면 연락주세요.",
            "view": "1"
        },
        {
            "no": "3",
            "title": "나의 2021년 목표",
            "content": "저의 2021년 목표는 컴활 1급 따기, 정보처리산업기사 자격증 따기 입니다.",
            "view": "1"
        },
        {
            "no": "4",
            "title": "나의 버킷리스트",
            "content": "저의 버킷리스트는 20대가 끝나기 전 유럽 배낭 여행 가기, 외국인 친구 사귀기, 번지점프 해보기 입니다.",
            "view": "1"
        },
        {
            "no": "5",
            "title": "나의 취미",
            "content": "저의 취미는 여행가기, 영화와 드라마 보기, 요리하기, 유튜브 영상 찍기 입니다.",
            "view": "1"
        },
        {
            "no": "6",
            "title": "내가 좋아하는 음식",
            "content": "제가 좋아하는 음식은 떡볶이, 파스타, 치킨, 피자입니다.",
            "view": "1"
        },
        {
            "no": "7",
            "title": "나의 좌우명",
            "content": "저의 취미는 손해보더라도 정직하게 살자",
            "view": "1"
        }
    ]
}